rai_sdk-0.7.7.dist-info/licenses/LICENSE
railib/__init__.py
railib/api.py
railib/config.py
railib/credentials.py
railib/rest.py
railib/show.py
railib/pb/__init__.py
railib/pb/message_pb2.py
railib/pb/schema_pb2.py
rai_sdk-0.7.7.dist-info/METADATA
rai_sdk-0.7.7.dist-info/WHEEL
rai_sdk-0.7.7.dist-info/top_level.txt
rai_sdk-0.7.7.dist-info/RECORD
